package/__init__.py
package/__main__.py
package/combinations.py
package/head.py
package/iterable_input.py
package/k_input.py
package1802/__init__.py
package1802/__main__.py
package1802/combinations.py
package1802/head.py
package1802/iterable_input.py
package1802/k_input.py
package_1802/__init__.py
package_1802/__main__.py
package_1802/combinations.py
package_1802/head.py
package_1802/iterable_input.py
package_1802/k_input.py
package_1802-1.0.dist-info/METADATA
package_1802-1.0.dist-info/WHEEL
package_1802-1.0.dist-info/top_level.txt
package_1802-1.0.dist-info/RECORD
