Metadata-Version: 2.1
Name: package-1802
Version: 1.0
Summary: calculating combinations without repetition
Home-page: UNKNOWN
Author: Periyanina Kseniya
License: UNKNOWN
Platform: UNKNOWN
